README.rst
setup.cfg
setup.py
lyricscreen/__init__.py
lyricscreen/__main__.py
lyricscreen/cli.py
lyricscreen/httpserver.py
lyricscreen/map.py
lyricscreen/playlist.py
lyricscreen/settings.py
lyricscreen/song.py
lyricscreen/utils.py
lyricscreen/verse.py
lyricscreen/wsserver.py
lyricscreen.egg-info/PKG-INFO
lyricscreen.egg-info/SOURCES.txt
lyricscreen.egg-info/dependency_links.txt
lyricscreen.egg-info/entry_points.txt
lyricscreen.egg-info/requires.txt
lyricscreen.egg-info/top_level.txt
lyricscreen/http/bower.json
lyricscreen/http/console.html
lyricscreen/http/display.html
lyricscreen/http/gulpfile.js
lyricscreen/http/package.json
lyricscreen/http/admin/index.html
lyricscreen/http/build/client.css
lyricscreen/http/build/console.js
lyricscreen/http/build/display.js
lyricscreen/http/console/index.html
lyricscreen/http/css/all.css
lyricscreen/http/css/client.css
lyricscreen/http/css/maps/client.css.map
lyricscreen/http/display/index.html
lyricscreen/http/fonts/FontAwesome.otf
lyricscreen/http/fonts/fontawesome-webfont.eot
lyricscreen/http/fonts/fontawesome-webfont.svg
lyricscreen/http/fonts/fontawesome-webfont.ttf
lyricscreen/http/fonts/fontawesome-webfont.woff
lyricscreen/http/js/console.js
lyricscreen/http/js/display.js
lyricscreen/http/sass/_googlefonts.scss
lyricscreen/http/sass/client.scss
lyricscreen/http/sass/fontawesome/_bordered-pulled.scss
lyricscreen/http/sass/fontawesome/_core.scss
lyricscreen/http/sass/fontawesome/_fixed-width.scss
lyricscreen/http/sass/fontawesome/_icons.scss
lyricscreen/http/sass/fontawesome/_larger.scss
lyricscreen/http/sass/fontawesome/_list.scss
lyricscreen/http/sass/fontawesome/_mixins.scss
lyricscreen/http/sass/fontawesome/_path.scss
lyricscreen/http/sass/fontawesome/_rotated-flipped.scss
lyricscreen/http/sass/fontawesome/_spinning.scss
lyricscreen/http/sass/fontawesome/_stacked.scss
lyricscreen/http/sass/fontawesome/_variables.scss
lyricscreen/http/sass/fontawesome/font-awesome.scss