Metadata-Version: 1.1
Name: lyricscreen
Version: 0.6.9
Summary: A lyrics management and display web app and server.
Home-page: https://github.com/lytedev/lyricscreen
Author: Daniel "lytedev" Flanagan
Author-email: daniel@lytedev.io
License: MIT
Keywords: lyrics lyric display presentation project projector
Platform: UNKNOWN
Classifier: Development Status :: 2 - Pre-Alpha
Classifier: Intended Audience :: Developers
Classifier: Intended Audience :: End Users/Desktop
Classifier: Intended Audience :: Information Technology
Classifier: Intended Audience :: Religion
Classifier: Intended Audience :: System Administrators
Classifier: Topic :: Communications
Classifier: Topic :: Communications :: Conferencing
Classifier: Topic :: Internet
Classifier: Topic :: Internet :: WWW/HTTP
Classifier: Topic :: Internet :: WWW/HTTP :: Dynamic Content
Classifier: Topic :: Multimedia :: Graphics :: Presentation
Classifier: Topic :: Multimedia :: Graphics :: Viewers
Classifier: Topic :: Religion
Classifier: License :: OSI Approved :: MIT License
Classifier: Programming Language :: Python :: 3.3
Classifier: Programming Language :: Python :: 3.4
